chimeralm/__init__.py
chimeralm/__main__.py
chimeralm/ui.py
chimeralm/data/__init__.py
chimeralm/data/bam.py
chimeralm/data/fq.py
chimeralm/data/only_fq.py
chimeralm/data/tokenizer.py
chimeralm/data/components/__init__.py
chimeralm/explain/__init__.py
chimeralm/explain/motif.py
chimeralm/models/__init__.py
chimeralm/models/basic_module.py
chimeralm/models/callbacks.py
chimeralm/models/lm.py
chimeralm/models/components/__init__.py
chimeralm/models/components/cnn.py
chimeralm/models/components/hyena.py
chimeralm/models/components/mamba.py
chimeralm/models/components/simple_dense_net.py
chimeralm/models/components/striped_hyena.py
chimeralm/models/components/transformer.py
chimeralm/utils/__init__.py
chimeralm/utils/instantiators.py
chimeralm/utils/logging_utils.py
chimeralm/utils/pylogger.py
chimeralm/utils/rich_utils.py
chimeralm/utils/utils.py
chimeralm-1.0.0.dist-info/METADATA
chimeralm-1.0.0.dist-info/WHEEL
chimeralm-1.0.0.dist-info/entry_points.txt
chimeralm-1.0.0.dist-info/licenses/LICENSE
chimeralm-1.0.0.dist-info/RECORD
