Metadata-Version: 2.4
Name: chimeralm
Version: 1.0.0
Summary: ChimeraLM: A genomic lanuage model to identify chimera artifact introduced by whole genome amplification (WGA).
Project-URL: homepage, https://github.com/ylab-hi/chimera
Project-URL: documentation, https://github.com/ylab-hi/chimera
Project-URL: repository, https://github.com/ylab-hi/chimera
Project-URL: changelog, https://github.com/ylab-hi/chimera/README.md
Author-email: Yangyang Li <yangyang.li@northwestern.edu>, Qingxiang Guo <qingxiang.guo@northwestern.edu>
License:                                  Apache License
License-File: LICENSE
Keywords: bioinformatics,deep learning,rust
Classifier: Development Status :: 5 - Production/Stable
Classifier: Environment :: Console
Classifier: Intended Audience :: Science/Research
Classifier: License :: OSI Approved :: Apache Software License
Classifier: Operating System :: OS Independent
Classifier: Programming Language :: Python
Classifier: Programming Language :: Python :: 3
Classifier: Programming Language :: Python :: 3 :: Only
Classifier: Programming Language :: Python :: 3.10
Classifier: Programming Language :: Python :: 3.11
Classifier: Programming Language :: Rust
Classifier: Topic :: Scientific/Engineering
Requires-Python: <3.12,>=3.10
Requires-Dist: datasets>=3.2.0
Requires-Dist: einops>=0.8.0
Requires-Dist: evaluate>=0.4.3
Requires-Dist: gradio>=4.0.0
Requires-Dist: hf-xet>=1.1.10
Requires-Dist: hydra-core>=1.3.2
Requires-Dist: joblib>=1.5.2
Requires-Dist: lightning>=2.4.0
Requires-Dist: needletail==0.5.0
Requires-Dist: omegaconf>=2.3.0
Requires-Dist: plotly>=5.0.0
Requires-Dist: pyfastx>=2.2.0
Requires-Dist: pysam>=0.22.1
Requires-Dist: rich>=13.9.4
Requires-Dist: torch==2.5.1
Requires-Dist: torchaudio>=2.5.0
Requires-Dist: torchmetrics>=1.6.0
Requires-Dist: torchvision>=0.20.1
Requires-Dist: transformers>=4.47.1
Requires-Dist: typer>=0.15.1
